rest_framework_datatables_editor/__init__.py
rest_framework_datatables_editor/filters.py
rest_framework_datatables_editor/pagination.py
rest_framework_datatables_editor/renderers.py
rest_framework_datatables_editor/viewsets.py
djangorestframework_datatables_editor-0.3.3.dist-info/LICENSE
djangorestframework_datatables_editor-0.3.3.dist-info/METADATA
djangorestframework_datatables_editor-0.3.3.dist-info/WHEEL
djangorestframework_datatables_editor-0.3.3.dist-info/top_level.txt
djangorestframework_datatables_editor-0.3.3.dist-info/RECORD
